retryx_deban/__init__.py
retryx_deban-0.1.0.dist-info/METADATA
retryx_deban-0.1.0.dist-info/WHEEL
retryx_deban-0.1.0.dist-info/RECORD
